{"character":"Mage","data":[{"action":"Walking","direction":"NE","frame_count":8,"frame_indices":[[0,0],[1,0],[2,0],[3,0],[0,1],[1,1],[2,1],[3,1]]},{"action":"Walking","direction":"SE","frame_count":8,"frame_indices":[[0,2],[1,2],[2,2],[3,2],[0,3],[1,3],[2,3],[3,3]]},{"action":"Attack","direction":"NE","frame_count":4,"frame_indices":[[0,4],[1,4],[2,4],[3,4]]},{"action":"Attack","direction":"SE","frame_count":4,"frame_indices":[[0,5],[1,5],[2,5],[3,5]]},{"action":"Release","direction":"NE","frame_count":1,"frame_indices":[[0,6]]},{"action":"Release","direction":"SE","frame_count":1,"frame_indices":[[0,7]]},{"action":"Charging","direction":"NE","frame_count":1,"frame_indices":[[0,8]]},{"action":"Charging","direction":"SE","frame_count":1,"frame_indices":[[0,9]]},{"action":"Damage","direction":"NE","frame_count":1,"frame_indices":[[0,10]]},{"action":"Damage","direction":"SE","frame_count":1,"frame_indices":[[0,11]]},{"action":"Weak","direction":"NE","frame_count":1,"frame_indices":[[0,12]]},{"action":"Weak","direction":"SE","frame_count":1,"frame_indices":[[0,13]]},{"action":"Dead","direction":"NE","frame_count":1,"frame_indices":[[0,14]]},{"action":"Dead","direction":"SE","frame_count":1,"frame_indices":[[0,15]]}]}